{"name":"mageFaker","tagline":"Fake / sample data generator for Magento","body":"mageFaker\r\n=========\r\n\r\n**Sample data generator for Magento [WIP]**\r\n\r\nThis simple module generates sample data for Magento. \r\nU can insert unlimited data of any type. It is not designed for showcase content, due to duplicated product names and limited images, but it is great for development / testing / benchmarking. It uses names and images from the Magento sample data package.\r\n\r\n#Features\r\n\r\n- Add any number of desired content. 1 - 10.000 products for example (large numbers can take a while)\r\n- Products can be assigned to any category (or multiple)\r\n- Multilayered categories\r\n- Remove any type of fake data, without losing \"real\" content\r\n\r\n#Currently supported data types\r\n\r\n - Categories\r\n - Simple products\r\n - Product reviews and ratings\r\n\r\n More to come.\r\n\r\n#Requirements\r\n\r\n- Magento            >= 1.9.0 (older versions untested)\r\n- PHP                >= 5.4\r\n- Memory limit       >= 512M\r\n- Unlimited max_execution_time preferred\r\n\r\n#How to use\r\n\r\n- Copy module files to your project root\r\n- Login to your Magento admin\r\n- Go to system -> Faker data\r\n- Choose your options and press start\r\n- Run indexer","google":"","note":"Don't delete this file! It's used internally to help with page regeneration."}